.gitignore
.gitmodules
CHANGES.txt
COPYRIGHT.rst
LICENSE.rst
README.rst
setup.cfg
setup.py
tox.ini
demo/.gitignore
demo/README.rst
demo/development.ini
demo/setup.cfg
demo/setup.py
demo/demo/__init__.py
demo/demo/layouts.py
demo/demo/panels.py
demo/demo/tests.py
demo/demo/views.py
demo/demo/static/css/bootstrap-responsive.min.css
demo/demo/static/css/bootstrap.min.css
demo/demo/static/img/glyphicons-halflings-white.png
demo/demo/static/img/glyphicons-halflings.png
demo/demo/static/js/bootstrap.min.js
demo/demo/static/js/jquery-1.8.0.min.js
demo/demo/templates/home.jinja2
demo/demo/templates/home.mako
demo/demo/templates/home.pt
demo/demo/templates/layouts/layout.jinja2
demo/demo/templates/layouts/layout.mako
demo/demo/templates/layouts/layout.pt
demo/demo/templates/panels/heading.jinja2
demo/demo/templates/panels/heading.mako
demo/demo/templates/panels/heading.pt
demo/demo/templates/panels/hero.mako
demo/demo/templates/panels/littlecat.pt
demo/demo/templates/panels/navbar.mako
demo/demo/templates/panels/thing.pt
demo/demo/templates/panels/usermenu.pt
docs/Makefile
docs/about.rst
docs/api.rst
docs/conf.py
docs/demo.rst
docs/glossary.rst
docs/index.rst
docs/layouts.rst
pyramid_layout/__init__.py
pyramid_layout/compat.py
pyramid_layout/config.py
pyramid_layout/configure.zcml
pyramid_layout/interfaces.py
pyramid_layout/layout.py
pyramid_layout/meta.zcml
pyramid_layout/panel.py
pyramid_layout/zcml.py
pyramid_layout.egg-info/PKG-INFO
pyramid_layout.egg-info/SOURCES.txt
pyramid_layout.egg-info/dependency_links.txt
pyramid_layout.egg-info/not-zip-safe
pyramid_layout.egg-info/requires.txt
pyramid_layout.egg-info/top_level.txt
pyramid_layout/tests/__init__.py
pyramid_layout/tests/test_config.py
pyramid_layout/tests/test_layout.py
pyramid_layout/tests/test_panel.py
pyramid_layout/tests/test_zcml.py
pyramid_layout/tests/microtemplates/a.mustache
pyramid_layout/tests/microtemplates/b.mustache
pyramid_layout/tests/microtemplates/wrong.ext